{
    "os": "Linux-5.13.0-39-generic-x86_64-with-glibc2.31",
    "python": "3.10.10",
    "heartbeatAt": "2023-05-05T19:27:01.087570",
    "startedAt": "2023-05-05T19:26:59.979426",
    "docker": null,
    "cuda": null,
    "args": [
        "--trial-num",
        "4",
        "--exp-group",
        "20230505-2326",
        "--acqf",
        "EIPU",
        "--decay-factor",
        "0"
    ],
    "state": "running",
    "program": "/home/abdelmajid/workdir/cost-aware-bo/main.py",
    "codePath": "main.py",
    "git": {
        "remote": "https://github.com/ridwan-salau/cost-aware-bo.git",
        "commit": "ee385b56d47047168cf713dbd130ab44d66541cc"
    },
    "email": null,
    "root": "/home/abdelmajid/workdir/cost-aware-bo",
    "host": "gpu-14",
    "username": "abdelmajid",
    "executable": "/home/abdelmajid/miniconda3/envs/tuun/bin/python",
    "cpu_count": 128,
    "cpu_count_logical": 256,
    "cpu_freq": {
        "current": 1766.8340859375,
        "min": 1500.0,
        "max": 2250.0
    },
    "cpu_freq_per_core": [
        {
            "current": 1500.0,
            "min": 1500.0,
            "max": 2250.0
        },
        {
            "current": 1500.0,
            "min": 1500.0,
            "max": 2250.0
        },
        {
            "current": 1371.254,
            "min": 1500.0,
            "max": 2250.0
        },
        {
            "current": 1500.0,
            "min": 1500.0,
            "max": 2250.0
        },
        {
            "current": 1500.0,
            "min": 1500.0,
            "max": 2250.0
        },
        {
            "current": 3344.255,
            "min": 1500.0,
            "max": 2250.0
        },
        {
            "current": 1500.0,
            "min": 1500.0,
            "max": 2250.0
        },
        {
            "current": 1500.0,
            "min": 1500.0,
            "max": 2250.0
        },
        {
            "current": 1500.0,
            "min": 1500.0,
            "max": 2250.0
        },
        {
            "current": 1765.079,
            "min": 1500.0,
            "max": 2250.0
        },
        {
            "current": 1500.0,
            "min": 1500.0,
            "max": 2250.0
        },
        {
            "current": 1500.0,
            "min": 1500.0,
            "max": 2250.0
        },
        {
            "current": 3343.911,
            "min": 1500.0,
            "max": 2250.0
        },
        {
            "current": 1485.028,
            "min": 1500.0,
            "max": 2250.0
        },
        {
            "current": 2707.925,
            "min": 1500.0,
            "max": 2250.0
        },
        {
            "current": 1500.0,
            "min": 1500.0,
            "max": 2250.0
        },
        {
            "current": 1500.0,
            "min": 1500.0,
            "max": 2250.0
        },
        {
            "current": 1500.0,
            "min": 1500.0,
            "max": 2250.0
        },
        {
            "current": 1500.0,
            "min": 1500.0,
            "max": 2250.0
        },
        {
            "current": 1500.0,
            "min": 1500.0,
            "max": 2250.0
        },
        {
            "current": 3161.124,
            "min": 1500.0,
            "max": 2250.0
        },
        {
            "current": 1655.652,
            "min": 1500.0,
            "max": 2250.0
        },
        {
            "current": 1474.616,
            "min": 1500.0,
            "max": 2250.0
        },
        {
            "current": 3345.944,
            "min": 1500.0,
            "max": 2250.0
        },
        {
            "current": 1500.0,
            "min": 1500.0,
            "max": 2250.0
        },
        {
            "current": 1524.471,
            "min": 1500.0,
            "max": 2250.0
        },
        {
            "current": 1500.0,
            "min": 1500.0,
            "max": 2250.0
        },
        {
            "current": 1500.0,
            "min": 1500.0,
            "max": 2250.0
        },
        {
            "current": 1499.213,
            "min": 1500.0,
            "max": 2250.0
        },
        {
            "current": 1498.874,
            "min": 1500.0,
            "max": 2250.0
        },
        {
            "current": 1500.0,
            "min": 1500.0,
            "max": 2250.0
        },
        {
            "current": 1500.0,
            "min": 1500.0,
            "max": 2250.0
        },
        {
            "current": 2250.0,
            "min": 1500.0,
            "max": 2250.0
        },
        {
            "current": 1500.0,
            "min": 1500.0,
            "max": 2250.0
        },
        {
            "current": 3283.34,
            "min": 1500.0,
            "max": 2250.0
        },
        {
            "current": 2000.0,
            "min": 1500.0,
            "max": 2250.0
        },
        {
            "current": 1453.523,
            "min": 1500.0,
            "max": 2250.0
        },
        {
            "current": 1500.0,
            "min": 1500.0,
            "max": 2250.0
        },
        {
            "current": 1694.651,
            "min": 1500.0,
            "max": 2250.0
        },
        {
            "current": 1505.85,
            "min": 1500.0,
            "max": 2250.0
        },
        {
            "current": 1500.0,
            "min": 1500.0,
            "max": 2250.0
        },
        {
            "current": 1500.0,
            "min": 1500.0,
            "max": 2250.0
        },
        {
            "current": 1500.0,
            "min": 1500.0,
            "max": 2250.0
        },
        {
            "current": 1500.0,
            "min": 1500.0,
            "max": 2250.0
        },
        {
            "current": 1500.0,
            "min": 1500.0,
            "max": 2250.0
        },
        {
            "current": 2031.932,
            "min": 1500.0,
            "max": 2250.0
        },
        {
            "current": 1721.304,
            "min": 1500.0,
            "max": 2250.0
        },
        {
            "current": 1500.0,
            "min": 1500.0,
            "max": 2250.0
        },
        {
            "current": 1500.0,
            "min": 1500.0,
            "max": 2250.0
        },
        {
            "current": 1485.375,
            "min": 1500.0,
            "max": 2250.0
        },
        {
            "current": 1500.0,
            "min": 1500.0,
            "max": 2250.0
        },
        {
            "current": 3197.401,
            "min": 1500.0,
            "max": 2250.0
        },
        {
            "current": 1500.0,
            "min": 1500.0,
            "max": 2250.0
        },
        {
            "current": 1500.0,
            "min": 1500.0,
            "max": 2250.0
        },
        {
            "current": 1501.114,
            "min": 1500.0,
            "max": 2250.0
        },
        {
            "current": 1500.0,
            "min": 1500.0,
            "max": 2250.0
        },
        {
            "current": 1500.0,
            "min": 1500.0,
            "max": 2250.0
        },
        {
            "current": 1549.24,
            "min": 1500.0,
            "max": 2250.0
        },
        {
            "current": 1500.0,
            "min": 1500.0,
            "max": 2250.0
        },
        {
            "current": 1506.836,
            "min": 1500.0,
            "max": 2250.0
        },
        {
            "current": 1479.369,
            "min": 1500.0,
            "max": 2250.0
        },
        {
            "current": 1500.0,
            "min": 1500.0,
            "max": 2250.0
        },
        {
            "current": 1500.0,
            "min": 1500.0,
            "max": 2250.0
        },
        {
            "current": 2000.0,
            "min": 1500.0,
            "max": 2250.0
        },
        {
            "current": 2850.802,
            "min": 1500.0,
            "max": 2250.0
        },
        {
            "current": 2250.0,
            "min": 1500.0,
            "max": 2250.0
        },
        {
            "current": 1500.0,
            "min": 1500.0,
            "max": 2250.0
        },
        {
            "current": 1624.894,
            "min": 1500.0,
            "max": 2250.0
        },
        {
            "current": 2250.0,
            "min": 1500.0,
            "max": 2250.0
        },
        {
            "current": 2842.41,
            "min": 1500.0,
            "max": 2250.0
        },
        {
            "current": 2250.0,
            "min": 1500.0,
            "max": 2250.0
        },
        {
            "current": 2802.663,
            "min": 1500.0,
            "max": 2250.0
        },
        {
            "current": 1500.0,
            "min": 1500.0,
            "max": 2250.0
        },
        {
            "current": 1500.0,
            "min": 1500.0,
            "max": 2250.0
        },
        {
            "current": 1500.0,
            "min": 1500.0,
            "max": 2250.0
        },
        {
            "current": 1500.0,
            "min": 1500.0,
            "max": 2250.0
        },
        {
            "current": 2250.0,
            "min": 1500.0,
            "max": 2250.0
        },
        {
            "current": 2900.077,
            "min": 1500.0,
            "max": 2250.0
        },
        {
            "current": 1500.0,
            "min": 1500.0,
            "max": 2250.0
        },
        {
            "current": 1500.0,
            "min": 1500.0,
            "max": 2250.0
        },
        {
            "current": 3250.624,
            "min": 1500.0,
            "max": 2250.0
        },
        {
            "current": 2250.0,
            "min": 1500.0,
            "max": 2250.0
        },
        {
            "current": 2250.0,
            "min": 1500.0,
            "max": 2250.0
        },
        {
            "current": 2858.409,
            "min": 1500.0,
            "max": 2250.0
        },
        {
            "current": 2798.392,
            "min": 1500.0,
            "max": 2250.0
        },
        {
            "current": 2250.0,
            "min": 1500.0,
            "max": 2250.0
        },
        {
            "current": 1449.146,
            "min": 1500.0,
            "max": 2250.0
        },
        {
            "current": 2619.683,
            "min": 1500.0,
            "max": 2250.0
        },
        {
            "current": 1500.0,
            "min": 1500.0,
            "max": 2250.0
        },
        {
            "current": 1515.651,
            "min": 1500.0,
            "max": 2250.0
        },
        {
            "current": 1500.0,
            "min": 1500.0,
            "max": 2250.0
        },
        {
            "current": 1500.0,
            "min": 1500.0,
            "max": 2250.0
        },
        {
            "current": 2365.711,
            "min": 1500.0,
            "max": 2250.0
        },
        {
            "current": 1500.0,
            "min": 1500.0,
            "max": 2250.0
        },
        {
            "current": 1500.0,
            "min": 1500.0,
            "max": 2250.0
        },
        {
            "current": 2250.0,
            "min": 1500.0,
            "max": 2250.0
        },
        {
            "current": 1500.0,
            "min": 1500.0,
            "max": 2250.0
        },
        {
            "current": 1500.0,
            "min": 1500.0,
            "max": 2250.0
        },
        {
            "current": 1500.0,
            "min": 1500.0,
            "max": 2250.0
        },
        {
            "current": 1500.0,
            "min": 1500.0,
            "max": 2250.0
        },
        {
            "current": 1500.0,
            "min": 1500.0,
            "max": 2250.0
        },
        {
            "current": 1452.547,
            "min": 1500.0,
            "max": 2250.0
        },
        {
            "current": 2796.736,
            "min": 1500.0,
            "max": 2250.0
        },
        {
            "current": 2250.0,
            "min": 1500.0,
            "max": 2250.0
        },
        {
            "current": 1500.0,
            "min": 1500.0,
            "max": 2250.0
        },
        {
            "current": 2664.837,
            "min": 1500.0,
            "max": 2250.0
        },
        {
            "current": 1500.0,
            "min": 1500.0,
            "max": 2250.0
        },
        {
            "current": 1484.907,
            "min": 1500.0,
            "max": 2250.0
        },
        {
            "current": 1500.0,
            "min": 1500.0,
            "max": 2250.0
        },
        {
            "current": 1508.094,
            "min": 1500.0,
            "max": 2250.0
        },
        {
            "current": 1500.0,
            "min": 1500.0,
            "max": 2250.0
        },
        {
            "current": 1500.0,
            "min": 1500.0,
            "max": 2250.0
        },
        {
            "current": 2996.875,
            "min": 1500.0,
            "max": 2250.0
        },
        {
            "current": 1469.092,
            "min": 1500.0,
            "max": 2250.0
        },
        {
            "current": 1444.786,
            "min": 1500.0,
            "max": 2250.0
        },
        {
            "current": 1500.0,
            "min": 1500.0,
            "max": 2250.0
        },
        {
            "current": 3252.094,
            "min": 1500.0,
            "max": 2250.0
        },
        {
            "current": 1500.0,
            "min": 1500.0,
            "max": 2250.0
        },
        {
            "current": 1500.0,
            "min": 1500.0,
            "max": 2250.0
        },
        {
            "current": 2250.0,
            "min": 1500.0,
            "max": 2250.0
        },
        {
            "current": 3250.683,
            "min": 1500.0,
            "max": 2250.0
        },
        {
            "current": 2850.381,
            "min": 1500.0,
            "max": 2250.0
        },
        {
            "current": 2975.05,
            "min": 1500.0,
            "max": 2250.0
        },
        {
            "current": 2250.0,
            "min": 1500.0,
            "max": 2250.0
        },
        {
            "current": 1500.0,
            "min": 1500.0,
            "max": 2250.0
        },
        {
            "current": 2568.59,
            "min": 1500.0,
            "max": 2250.0
        },
        {
            "current": 1500.0,
            "min": 1500.0,
            "max": 2250.0
        },
        {
            "current": 1500.0,
            "min": 1500.0,
            "max": 2250.0
        },
        {
            "current": 1936.511,
            "min": 1500.0,
            "max": 2250.0
        },
        {
            "current": 1500.0,
            "min": 1500.0,
            "max": 2250.0
        },
        {
            "current": 1402.963,
            "min": 1500.0,
            "max": 2250.0
        },
        {
            "current": 1500.0,
            "min": 1500.0,
            "max": 2250.0
        },
        {
            "current": 1900.364,
            "min": 1500.0,
            "max": 2250.0
        },
        {
            "current": 2219.68,
            "min": 1500.0,
            "max": 2250.0
        },
        {
            "current": 2802.221,
            "min": 1500.0,
            "max": 2250.0
        },
        {
            "current": 1500.0,
            "min": 1500.0,
            "max": 2250.0
        },
        {
            "current": 1500.0,
            "min": 1500.0,
            "max": 2250.0
        },
        {
            "current": 1500.0,
            "min": 1500.0,
            "max": 2250.0
        },
        {
            "current": 1500.0,
            "min": 1500.0,
            "max": 2250.0
        },
        {
            "current": 1479.711,
            "min": 1500.0,
            "max": 2250.0
        },
        {
            "current": 3338.448,
            "min": 1500.0,
            "max": 2250.0
        },
        {
            "current": 2171.706,
            "min": 1500.0,
            "max": 2250.0
        },
        {
            "current": 3122.208,
            "min": 1500.0,
            "max": 2250.0
        },
        {
            "current": 2393.341,
            "min": 1500.0,
            "max": 2250.0
        },
        {
            "current": 1522.864,
            "min": 1500.0,
            "max": 2250.0
        },
        {
            "current": 1500.0,
            "min": 1500.0,
            "max": 2250.0
        },
        {
            "current": 1494.839,
            "min": 1500.0,
            "max": 2250.0
        },
        {
            "current": 1493.132,
            "min": 1500.0,
            "max": 2250.0
        },
        {
            "current": 1725.909,
            "min": 1500.0,
            "max": 2250.0
        },
        {
            "current": 1734.574,
            "min": 1500.0,
            "max": 2250.0
        },
        {
            "current": 3011.169,
            "min": 1500.0,
            "max": 2250.0
        },
        {
            "current": 3282.863,
            "min": 1500.0,
            "max": 2250.0
        },
        {
            "current": 1489.616,
            "min": 1500.0,
            "max": 2250.0
        },
        {
            "current": 1574.973,
            "min": 1500.0,
            "max": 2250.0
        },
        {
            "current": 1500.0,
            "min": 1500.0,
            "max": 2250.0
        },
        {
            "current": 1500.0,
            "min": 1500.0,
            "max": 2250.0
        },
        {
            "current": 1500.0,
            "min": 1500.0,
            "max": 2250.0
        },
        {
            "current": 1625.532,
            "min": 1500.0,
            "max": 2250.0
        },
        {
            "current": 1743.095,
            "min": 1500.0,
            "max": 2250.0
        },
        {
            "current": 3188.064,
            "min": 1500.0,
            "max": 2250.0
        },
        {
            "current": 1500.0,
            "min": 1500.0,
            "max": 2250.0
        },
        {
            "current": 3345.598,
            "min": 1500.0,
            "max": 2250.0
        },
        {
            "current": 2478.585,
            "min": 1500.0,
            "max": 2250.0
        },
        {
            "current": 1911.959,
            "min": 1500.0,
            "max": 2250.0
        },
        {
            "current": 1396.079,
            "min": 1500.0,
            "max": 2250.0
        },
        {
            "current": 1403.488,
            "min": 1500.0,
            "max": 2250.0
        },
        {
            "current": 1357.824,
            "min": 1500.0,
            "max": 2250.0
        },
        {
            "current": 1672.899,
            "min": 1500.0,
            "max": 2250.0
        },
        {
            "current": 1500.0,
            "min": 1500.0,
            "max": 2250.0
        },
        {
            "current": 1500.0,
            "min": 1500.0,
            "max": 2250.0
        },
        {
            "current": 1603.243,
            "min": 1500.0,
            "max": 2250.0
        },
        {
            "current": 2000.0,
            "min": 1500.0,
            "max": 2250.0
        },
        {
            "current": 1500.0,
            "min": 1500.0,
            "max": 2250.0
        },
        {
            "current": 2602.901,
            "min": 1500.0,
            "max": 2250.0
        },
        {
            "current": 1627.102,
            "min": 1500.0,
            "max": 2250.0
        },
        {
            "current": 1478.238,
            "min": 1500.0,
            "max": 2250.0
        },
        {
            "current": 3342.254,
            "min": 1500.0,
            "max": 2250.0
        },
        {
            "current": 1484.082,
            "min": 1500.0,
            "max": 2250.0
        },
        {
            "current": 1466.115,
            "min": 1500.0,
            "max": 2250.0
        },
        {
            "current": 2439.742,
            "min": 1500.0,
            "max": 2250.0
        },
        {
            "current": 1434.402,
            "min": 1500.0,
            "max": 2250.0
        },
        {
            "current": 1720.686,
            "min": 1500.0,
            "max": 2250.0
        },
        {
            "current": 1477.15,
            "min": 1500.0,
            "max": 2250.0
        },
        {
            "current": 1500.0,
            "min": 1500.0,
            "max": 2250.0
        },
        {
            "current": 1488.736,
            "min": 1500.0,
            "max": 2250.0
        },
        {
            "current": 1516.868,
            "min": 1500.0,
            "max": 2250.0
        },
        {
            "current": 1500.0,
            "min": 1500.0,
            "max": 2250.0
        },
        {
            "current": 1489.622,
            "min": 1500.0,
            "max": 2250.0
        },
        {
            "current": 1500.0,
            "min": 1500.0,
            "max": 2250.0
        },
        {
            "current": 1500.0,
            "min": 1500.0,
            "max": 2250.0
        },
        {
            "current": 1500.0,
            "min": 1500.0,
            "max": 2250.0
        },
        {
            "current": 1500.0,
            "min": 1500.0,
            "max": 2250.0
        },
        {
            "current": 1500.0,
            "min": 1500.0,
            "max": 2250.0
        },
        {
            "current": 3005.321,
            "min": 1500.0,
            "max": 2250.0
        },
        {
            "current": 1461.145,
            "min": 1500.0,
            "max": 2250.0
        },
        {
            "current": 1443.807,
            "min": 1500.0,
            "max": 2250.0
        },
        {
            "current": 1500.0,
            "min": 1500.0,
            "max": 2250.0
        },
        {
            "current": 1500.0,
            "min": 1500.0,
            "max": 2250.0
        },
        {
            "current": 1500.0,
            "min": 1500.0,
            "max": 2250.0
        },
        {
            "current": 1500.0,
            "min": 1500.0,
            "max": 2250.0
        },
        {
            "current": 1500.0,
            "min": 1500.0,
            "max": 2250.0
        },
        {
            "current": 2250.0,
            "min": 1500.0,
            "max": 2250.0
        },
        {
            "current": 2250.0,
            "min": 1500.0,
            "max": 2250.0
        },
        {
            "current": 2250.0,
            "min": 1500.0,
            "max": 2250.0
        },
        {
            "current": 1500.0,
            "min": 1500.0,
            "max": 2250.0
        },
        {
            "current": 2250.0,
            "min": 1500.0,
            "max": 2250.0
        },
        {
            "current": 2250.0,
            "min": 1500.0,
            "max": 2250.0
        },
        {
            "current": 2250.0,
            "min": 1500.0,
            "max": 2250.0
        },
        {
            "current": 2940.66,
            "min": 1500.0,
            "max": 2250.0
        },
        {
            "current": 2795.137,
            "min": 1500.0,
            "max": 2250.0
        },
        {
            "current": 2877.361,
            "min": 1500.0,
            "max": 2250.0
        },
        {
            "current": 2250.0,
            "min": 1500.0,
            "max": 2250.0
        },
        {
            "current": 2980.354,
            "min": 1500.0,
            "max": 2250.0
        },
        {
            "current": 2993.912,
            "min": 1500.0,
            "max": 2250.0
        },
        {
            "current": 1436.62,
            "min": 1500.0,
            "max": 2250.0
        },
        {
            "current": 1500.0,
            "min": 1500.0,
            "max": 2250.0
        },
        {
            "current": 1964.165,
            "min": 1500.0,
            "max": 2250.0
        },
        {
            "current": 2142.393,
            "min": 1500.0,
            "max": 2250.0
        },
        {
            "current": 1500.0,
            "min": 1500.0,
            "max": 2250.0
        },
        {
            "current": 2576.182,
            "min": 1500.0,
            "max": 2250.0
        },
        {
            "current": 1500.0,
            "min": 1500.0,
            "max": 2250.0
        },
        {
            "current": 1500.0,
            "min": 1500.0,
            "max": 2250.0
        },
        {
            "current": 1911.215,
            "min": 1500.0,
            "max": 2250.0
        },
        {
            "current": 3029.828,
            "min": 1500.0,
            "max": 2250.0
        },
        {
            "current": 2250.0,
            "min": 1500.0,
            "max": 2250.0
        },
        {
            "current": 1500.0,
            "min": 1500.0,
            "max": 2250.0
        },
        {
            "current": 1500.0,
            "min": 1500.0,
            "max": 2250.0
        },
        {
            "current": 2250.0,
            "min": 1500.0,
            "max": 2250.0
        },
        {
            "current": 2808.191,
            "min": 1500.0,
            "max": 2250.0
        },
        {
            "current": 1500.0,
            "min": 1500.0,
            "max": 2250.0
        },
        {
            "current": 2978.309,
            "min": 1500.0,
            "max": 2250.0
        },
        {
            "current": 3217.291,
            "min": 1500.0,
            "max": 2250.0
        },
        {
            "current": 2250.0,
            "min": 1500.0,
            "max": 2250.0
        },
        {
            "current": 2293.041,
            "min": 1500.0,
            "max": 2250.0
        },
        {
            "current": 1474.813,
            "min": 1500.0,
            "max": 2250.0
        },
        {
            "current": 2000.0,
            "min": 1500.0,
            "max": 2250.0
        },
        {
            "current": 1500.0,
            "min": 1500.0,
            "max": 2250.0
        },
        {
            "current": 1495.048,
            "min": 1500.0,
            "max": 2250.0
        },
        {
            "current": 1500.0,
            "min": 1500.0,
            "max": 2250.0
        },
        {
            "current": 1500.0,
            "min": 1500.0,
            "max": 2250.0
        },
        {
            "current": 2250.0,
            "min": 1500.0,
            "max": 2250.0
        },
        {
            "current": 1636.912,
            "min": 1500.0,
            "max": 2250.0
        },
        {
            "current": 1500.0,
            "min": 1500.0,
            "max": 2250.0
        },
        {
            "current": 2000.0,
            "min": 1500.0,
            "max": 2250.0
        },
        {
            "current": 2250.0,
            "min": 1500.0,
            "max": 2250.0
        },
        {
            "current": 3058.317,
            "min": 1500.0,
            "max": 2250.0
        },
        {
            "current": 1500.0,
            "min": 1500.0,
            "max": 2250.0
        },
        {
            "current": 3065.841,
            "min": 1500.0,
            "max": 2250.0
        },
        {
            "current": 1500.0,
            "min": 1500.0,
            "max": 2250.0
        },
        {
            "current": 2250.0,
            "min": 1500.0,
            "max": 2250.0
        },
        {
            "current": 2898.155,
            "min": 1500.0,
            "max": 2250.0
        },
        {
            "current": 3076.359,
            "min": 1500.0,
            "max": 2250.0
        },
        {
            "current": 3190.075,
            "min": 1500.0,
            "max": 2250.0
        },
        {
            "current": 1500.0,
            "min": 1500.0,
            "max": 2250.0
        },
        {
            "current": 1500.0,
            "min": 1500.0,
            "max": 2250.0
        },
        {
            "current": 2250.0,
            "min": 1500.0,
            "max": 2250.0
        }
    ],
    "disk": {
        "total": 3724.1025772094727,
        "used": 122.16918182373047
    },
    "gpu": "NVIDIA A100-SXM4-40GB",
    "gpu_count": 4,
    "gpu_devices": [
        {
            "name": "NVIDIA A100-SXM4-40GB",
            "memory_total": 42949672960
        },
        {
            "name": "NVIDIA A100-SXM4-40GB",
            "memory_total": 42949672960
        },
        {
            "name": "NVIDIA A100-SXM4-40GB",
            "memory_total": 42949672960
        },
        {
            "name": "NVIDIA A100-SXM4-40GB",
            "memory_total": 42949672960
        }
    ],
    "memory": {
        "total": 251.68415451049805
    }
}
