{
    "os": "Linux-5.13.0-39-generic-x86_64-with-glibc2.31",
    "python": "3.10.10",
    "heartbeatAt": "2023-05-05T13:42:52.625079",
    "startedAt": "2023-05-05T13:42:51.706179",
    "docker": null,
    "cuda": null,
    "args": [
        "--trial-num",
        "2",
        "--exp-group",
        "20230505-1742",
        "--acqf",
        "EIPU"
    ],
    "state": "running",
    "program": "/home/abdelmajid/workdir/cost-aware-bo/main.py",
    "codePath": "main.py",
    "git": {
        "remote": "https://github.com/ridwan-salau/cost-aware-bo.git",
        "commit": "ee385b56d47047168cf713dbd130ab44d66541cc"
    },
    "email": null,
    "root": "/home/abdelmajid/workdir/cost-aware-bo",
    "host": "gpu-14",
    "username": "abdelmajid",
    "executable": "/home/abdelmajid/miniconda3/envs/tuun/bin/python",
    "cpu_count": 128,
    "cpu_count_logical": 256,
    "cpu_freq": {
        "current": 2525.5607812499998,
        "min": 1500.0,
        "max": 2250.0
    },
    "cpu_freq_per_core": [
        {
            "current": 1747.947,
            "min": 1500.0,
            "max": 2250.0
        },
        {
            "current": 3062.119,
            "min": 1500.0,
            "max": 2250.0
        },
        {
            "current": 3062.053,
            "min": 1500.0,
            "max": 2250.0
        },
        {
            "current": 3062.116,
            "min": 1500.0,
            "max": 2250.0
        },
        {
            "current": 3057.511,
            "min": 1500.0,
            "max": 2250.0
        },
        {
            "current": 3057.838,
            "min": 1500.0,
            "max": 2250.0
        },
        {
            "current": 3057.637,
            "min": 1500.0,
            "max": 2250.0
        },
        {
            "current": 3057.707,
            "min": 1500.0,
            "max": 2250.0
        },
        {
            "current": 3061.786,
            "min": 1500.0,
            "max": 2250.0
        },
        {
            "current": 2768.311,
            "min": 1500.0,
            "max": 2250.0
        },
        {
            "current": 3061.719,
            "min": 1500.0,
            "max": 2250.0
        },
        {
            "current": 1500.0,
            "min": 1500.0,
            "max": 2250.0
        },
        {
            "current": 2000.0,
            "min": 1500.0,
            "max": 2250.0
        },
        {
            "current": 3060.863,
            "min": 1500.0,
            "max": 2250.0
        },
        {
            "current": 3060.848,
            "min": 1500.0,
            "max": 2250.0
        },
        {
            "current": 3060.794,
            "min": 1500.0,
            "max": 2250.0
        },
        {
            "current": 1500.0,
            "min": 1500.0,
            "max": 2250.0
        },
        {
            "current": 3060.529,
            "min": 1500.0,
            "max": 2250.0
        },
        {
            "current": 3060.729,
            "min": 1500.0,
            "max": 2250.0
        },
        {
            "current": 3060.598,
            "min": 1500.0,
            "max": 2250.0
        },
        {
            "current": 3061.866,
            "min": 1500.0,
            "max": 2250.0
        },
        {
            "current": 3061.668,
            "min": 1500.0,
            "max": 2250.0
        },
        {
            "current": 3061.734,
            "min": 1500.0,
            "max": 2250.0
        },
        {
            "current": 3061.667,
            "min": 1500.0,
            "max": 2250.0
        },
        {
            "current": 3059.691,
            "min": 1500.0,
            "max": 2250.0
        },
        {
            "current": 1500.0,
            "min": 1500.0,
            "max": 2250.0
        },
        {
            "current": 3059.625,
            "min": 1500.0,
            "max": 2250.0
        },
        {
            "current": 3059.692,
            "min": 1500.0,
            "max": 2250.0
        },
        {
            "current": 1500.0,
            "min": 1500.0,
            "max": 2250.0
        },
        {
            "current": 3061.859,
            "min": 1500.0,
            "max": 2250.0
        },
        {
            "current": 3061.923,
            "min": 1500.0,
            "max": 2250.0
        },
        {
            "current": 3061.926,
            "min": 1500.0,
            "max": 2250.0
        },
        {
            "current": 1500.0,
            "min": 1500.0,
            "max": 2250.0
        },
        {
            "current": 3062.824,
            "min": 1500.0,
            "max": 2250.0
        },
        {
            "current": 3062.835,
            "min": 1500.0,
            "max": 2250.0
        },
        {
            "current": 1500.0,
            "min": 1500.0,
            "max": 2250.0
        },
        {
            "current": 1500.0,
            "min": 1500.0,
            "max": 2250.0
        },
        {
            "current": 3060.728,
            "min": 1500.0,
            "max": 2250.0
        },
        {
            "current": 2342.471,
            "min": 1500.0,
            "max": 2250.0
        },
        {
            "current": 1500.0,
            "min": 1500.0,
            "max": 2250.0
        },
        {
            "current": 3062.846,
            "min": 1500.0,
            "max": 2250.0
        },
        {
            "current": 3062.846,
            "min": 1500.0,
            "max": 2250.0
        },
        {
            "current": 3062.78,
            "min": 1500.0,
            "max": 2250.0
        },
        {
            "current": 3062.846,
            "min": 1500.0,
            "max": 2250.0
        },
        {
            "current": 3062.907,
            "min": 1500.0,
            "max": 2250.0
        },
        {
            "current": 3062.963,
            "min": 1500.0,
            "max": 2250.0
        },
        {
            "current": 3062.974,
            "min": 1500.0,
            "max": 2250.0
        },
        {
            "current": 1500.0,
            "min": 1500.0,
            "max": 2250.0
        },
        {
            "current": 3059.552,
            "min": 1500.0,
            "max": 2250.0
        },
        {
            "current": 3059.419,
            "min": 1500.0,
            "max": 2250.0
        },
        {
            "current": 1500.0,
            "min": 1500.0,
            "max": 2250.0
        },
        {
            "current": 3059.553,
            "min": 1500.0,
            "max": 2250.0
        },
        {
            "current": 3062.978,
            "min": 1500.0,
            "max": 2250.0
        },
        {
            "current": 1500.0,
            "min": 1500.0,
            "max": 2250.0
        },
        {
            "current": 1500.0,
            "min": 1500.0,
            "max": 2250.0
        },
        {
            "current": 2250.0,
            "min": 1500.0,
            "max": 2250.0
        },
        {
            "current": 3062.707,
            "min": 1500.0,
            "max": 2250.0
        },
        {
            "current": 2250.0,
            "min": 1500.0,
            "max": 2250.0
        },
        {
            "current": 1500.0,
            "min": 1500.0,
            "max": 2250.0
        },
        {
            "current": 3062.776,
            "min": 1500.0,
            "max": 2250.0
        },
        {
            "current": 3062.965,
            "min": 1500.0,
            "max": 2250.0
        },
        {
            "current": 3062.844,
            "min": 1500.0,
            "max": 2250.0
        },
        {
            "current": 3062.883,
            "min": 1500.0,
            "max": 2250.0
        },
        {
            "current": 1500.0,
            "min": 1500.0,
            "max": 2250.0
        },
        {
            "current": 1500.0,
            "min": 1500.0,
            "max": 2250.0
        },
        {
            "current": 1500.0,
            "min": 1500.0,
            "max": 2250.0
        },
        {
            "current": 3130.966,
            "min": 1500.0,
            "max": 2250.0
        },
        {
            "current": 3127.985,
            "min": 1500.0,
            "max": 2250.0
        },
        {
            "current": 2000.0,
            "min": 1500.0,
            "max": 2250.0
        },
        {
            "current": 1500.0,
            "min": 1500.0,
            "max": 2250.0
        },
        {
            "current": 1500.0,
            "min": 1500.0,
            "max": 2250.0
        },
        {
            "current": 2250.0,
            "min": 1500.0,
            "max": 2250.0
        },
        {
            "current": 2250.0,
            "min": 1500.0,
            "max": 2250.0
        },
        {
            "current": 3115.48,
            "min": 1500.0,
            "max": 2250.0
        },
        {
            "current": 3128.813,
            "min": 1500.0,
            "max": 2250.0
        },
        {
            "current": 1500.0,
            "min": 1500.0,
            "max": 2250.0
        },
        {
            "current": 1500.0,
            "min": 1500.0,
            "max": 2250.0
        },
        {
            "current": 3117.672,
            "min": 1500.0,
            "max": 2250.0
        },
        {
            "current": 3115.113,
            "min": 1500.0,
            "max": 2250.0
        },
        {
            "current": 2250.0,
            "min": 1500.0,
            "max": 2250.0
        },
        {
            "current": 3117.362,
            "min": 1500.0,
            "max": 2250.0
        },
        {
            "current": 3124.038,
            "min": 1500.0,
            "max": 2250.0
        },
        {
            "current": 1500.0,
            "min": 1500.0,
            "max": 2250.0
        },
        {
            "current": 3129.775,
            "min": 1500.0,
            "max": 2250.0
        },
        {
            "current": 1500.0,
            "min": 1500.0,
            "max": 2250.0
        },
        {
            "current": 1500.0,
            "min": 1500.0,
            "max": 2250.0
        },
        {
            "current": 1500.0,
            "min": 1500.0,
            "max": 2250.0
        },
        {
            "current": 1500.0,
            "min": 1500.0,
            "max": 2250.0
        },
        {
            "current": 1500.0,
            "min": 1500.0,
            "max": 2250.0
        },
        {
            "current": 1500.0,
            "min": 1500.0,
            "max": 2250.0
        },
        {
            "current": 3118.672,
            "min": 1500.0,
            "max": 2250.0
        },
        {
            "current": 2250.0,
            "min": 1500.0,
            "max": 2250.0
        },
        {
            "current": 2250.0,
            "min": 1500.0,
            "max": 2250.0
        },
        {
            "current": 3130.52,
            "min": 1500.0,
            "max": 2250.0
        },
        {
            "current": 3114.971,
            "min": 1500.0,
            "max": 2250.0
        },
        {
            "current": 3115.99,
            "min": 1500.0,
            "max": 2250.0
        },
        {
            "current": 3130.703,
            "min": 1500.0,
            "max": 2250.0
        },
        {
            "current": 3101.341,
            "min": 1500.0,
            "max": 2250.0
        },
        {
            "current": 3121.159,
            "min": 1500.0,
            "max": 2250.0
        },
        {
            "current": 1500.0,
            "min": 1500.0,
            "max": 2250.0
        },
        {
            "current": 1500.0,
            "min": 1500.0,
            "max": 2250.0
        },
        {
            "current": 3122.862,
            "min": 1500.0,
            "max": 2250.0
        },
        {
            "current": 2890.265,
            "min": 1500.0,
            "max": 2250.0
        },
        {
            "current": 1500.0,
            "min": 1500.0,
            "max": 2250.0
        },
        {
            "current": 1500.0,
            "min": 1500.0,
            "max": 2250.0
        },
        {
            "current": 3155.345,
            "min": 1500.0,
            "max": 2250.0
        },
        {
            "current": 1500.0,
            "min": 1500.0,
            "max": 2250.0
        },
        {
            "current": 3122.479,
            "min": 1500.0,
            "max": 2250.0
        },
        {
            "current": 3150.92,
            "min": 1500.0,
            "max": 2250.0
        },
        {
            "current": 1500.0,
            "min": 1500.0,
            "max": 2250.0
        },
        {
            "current": 3123.176,
            "min": 1500.0,
            "max": 2250.0
        },
        {
            "current": 2250.0,
            "min": 1500.0,
            "max": 2250.0
        },
        {
            "current": 3125.969,
            "min": 1500.0,
            "max": 2250.0
        },
        {
            "current": 2250.0,
            "min": 1500.0,
            "max": 2250.0
        },
        {
            "current": 1500.0,
            "min": 1500.0,
            "max": 2250.0
        },
        {
            "current": 3123.484,
            "min": 1500.0,
            "max": 2250.0
        },
        {
            "current": 1500.0,
            "min": 1500.0,
            "max": 2250.0
        },
        {
            "current": 3126.817,
            "min": 1500.0,
            "max": 2250.0
        },
        {
            "current": 3140.108,
            "min": 1500.0,
            "max": 2250.0
        },
        {
            "current": 3119.485,
            "min": 1500.0,
            "max": 2250.0
        },
        {
            "current": 3122.573,
            "min": 1500.0,
            "max": 2250.0
        },
        {
            "current": 1500.0,
            "min": 1500.0,
            "max": 2250.0
        },
        {
            "current": 2000.0,
            "min": 1500.0,
            "max": 2250.0
        },
        {
            "current": 2250.0,
            "min": 1500.0,
            "max": 2250.0
        },
        {
            "current": 1500.0,
            "min": 1500.0,
            "max": 2250.0
        },
        {
            "current": 1500.0,
            "min": 1500.0,
            "max": 2250.0
        },
        {
            "current": 1500.0,
            "min": 1500.0,
            "max": 2250.0
        },
        {
            "current": 3116.817,
            "min": 1500.0,
            "max": 2250.0
        },
        {
            "current": 1500.0,
            "min": 1500.0,
            "max": 2250.0
        },
        {
            "current": 1500.0,
            "min": 1500.0,
            "max": 2250.0
        },
        {
            "current": 3061.971,
            "min": 1500.0,
            "max": 2250.0
        },
        {
            "current": 1500.0,
            "min": 1500.0,
            "max": 2250.0
        },
        {
            "current": 3057.374,
            "min": 1500.0,
            "max": 2250.0
        },
        {
            "current": 3057.701,
            "min": 1500.0,
            "max": 2250.0
        },
        {
            "current": 2250.0,
            "min": 1500.0,
            "max": 2250.0
        },
        {
            "current": 3057.573,
            "min": 1500.0,
            "max": 2250.0
        },
        {
            "current": 3061.685,
            "min": 1500.0,
            "max": 2250.0
        },
        {
            "current": 1500.0,
            "min": 1500.0,
            "max": 2250.0
        },
        {
            "current": 1500.0,
            "min": 1500.0,
            "max": 2250.0
        },
        {
            "current": 3061.686,
            "min": 1500.0,
            "max": 2250.0
        },
        {
            "current": 2446.312,
            "min": 1500.0,
            "max": 2250.0
        },
        {
            "current": 2250.0,
            "min": 1500.0,
            "max": 2250.0
        },
        {
            "current": 1500.0,
            "min": 1500.0,
            "max": 2250.0
        },
        {
            "current": 1500.0,
            "min": 1500.0,
            "max": 2250.0
        },
        {
            "current": 3060.542,
            "min": 1500.0,
            "max": 2250.0
        },
        {
            "current": 1500.0,
            "min": 1500.0,
            "max": 2250.0
        },
        {
            "current": 1500.0,
            "min": 1500.0,
            "max": 2250.0
        },
        {
            "current": 3060.489,
            "min": 1500.0,
            "max": 2250.0
        },
        {
            "current": 3061.765,
            "min": 1500.0,
            "max": 2250.0
        },
        {
            "current": 3061.569,
            "min": 1500.0,
            "max": 2250.0
        },
        {
            "current": 1500.0,
            "min": 1500.0,
            "max": 2250.0
        },
        {
            "current": 1500.0,
            "min": 1500.0,
            "max": 2250.0
        },
        {
            "current": 2250.0,
            "min": 1500.0,
            "max": 2250.0
        },
        {
            "current": 3059.508,
            "min": 1500.0,
            "max": 2250.0
        },
        {
            "current": 3063.833,
            "min": 1500.0,
            "max": 2250.0
        },
        {
            "current": 3059.576,
            "min": 1500.0,
            "max": 2250.0
        },
        {
            "current": 2264.088,
            "min": 1500.0,
            "max": 2250.0
        },
        {
            "current": 2000.0,
            "min": 1500.0,
            "max": 2250.0
        },
        {
            "current": 3062.891,
            "min": 1500.0,
            "max": 2250.0
        },
        {
            "current": 3062.891,
            "min": 1500.0,
            "max": 2250.0
        },
        {
            "current": 1500.0,
            "min": 1500.0,
            "max": 2250.0
        },
        {
            "current": 3062.678,
            "min": 1500.0,
            "max": 2250.0
        },
        {
            "current": 3062.689,
            "min": 1500.0,
            "max": 2250.0
        },
        {
            "current": 3062.689,
            "min": 1500.0,
            "max": 2250.0
        },
        {
            "current": 3060.625,
            "min": 1500.0,
            "max": 2250.0
        },
        {
            "current": 3060.56,
            "min": 1500.0,
            "max": 2250.0
        },
        {
            "current": 1500.0,
            "min": 1500.0,
            "max": 2250.0
        },
        {
            "current": 3060.535,
            "min": 1500.0,
            "max": 2250.0
        },
        {
            "current": 3062.701,
            "min": 1500.0,
            "max": 2250.0
        },
        {
            "current": 1500.0,
            "min": 1500.0,
            "max": 2250.0
        },
        {
            "current": 3062.635,
            "min": 1500.0,
            "max": 2250.0
        },
        {
            "current": 3063.674,
            "min": 1500.0,
            "max": 2250.0
        },
        {
            "current": 3062.763,
            "min": 1500.0,
            "max": 2250.0
        },
        {
            "current": 3062.816,
            "min": 1500.0,
            "max": 2250.0
        },
        {
            "current": 3062.829,
            "min": 1500.0,
            "max": 2250.0
        },
        {
            "current": 3062.833,
            "min": 1500.0,
            "max": 2250.0
        },
        {
            "current": 3059.366,
            "min": 1500.0,
            "max": 2250.0
        },
        {
            "current": 3059.232,
            "min": 1500.0,
            "max": 2250.0
        },
        {
            "current": 3059.498,
            "min": 1500.0,
            "max": 2250.0
        },
        {
            "current": 3059.369,
            "min": 1500.0,
            "max": 2250.0
        },
        {
            "current": 3062.836,
            "min": 1500.0,
            "max": 2250.0
        },
        {
            "current": 3062.814,
            "min": 1500.0,
            "max": 2250.0
        },
        {
            "current": 3062.811,
            "min": 1500.0,
            "max": 2250.0
        },
        {
            "current": 3062.835,
            "min": 1500.0,
            "max": 2250.0
        },
        {
            "current": 3062.566,
            "min": 1500.0,
            "max": 2250.0
        },
        {
            "current": 3062.7,
            "min": 1500.0,
            "max": 2250.0
        },
        {
            "current": 3062.7,
            "min": 1500.0,
            "max": 2250.0
        },
        {
            "current": 1500.0,
            "min": 1500.0,
            "max": 2250.0
        },
        {
            "current": 2000.0,
            "min": 1500.0,
            "max": 2250.0
        },
        {
            "current": 3062.705,
            "min": 1500.0,
            "max": 2250.0
        },
        {
            "current": 1500.0,
            "min": 1500.0,
            "max": 2250.0
        },
        {
            "current": 3062.772,
            "min": 1500.0,
            "max": 2250.0
        },
        {
            "current": 1444.851,
            "min": 1500.0,
            "max": 2250.0
        },
        {
            "current": 3115.337,
            "min": 1500.0,
            "max": 2250.0
        },
        {
            "current": 1500.0,
            "min": 1500.0,
            "max": 2250.0
        },
        {
            "current": 3114.919,
            "min": 1500.0,
            "max": 2250.0
        },
        {
            "current": 2000.0,
            "min": 1500.0,
            "max": 2250.0
        },
        {
            "current": 2250.0,
            "min": 1500.0,
            "max": 2250.0
        },
        {
            "current": 2000.0,
            "min": 1500.0,
            "max": 2250.0
        },
        {
            "current": 3113.524,
            "min": 1500.0,
            "max": 2250.0
        },
        {
            "current": 2581.249,
            "min": 1500.0,
            "max": 2250.0
        },
        {
            "current": 1500.0,
            "min": 1500.0,
            "max": 2250.0
        },
        {
            "current": 3128.505,
            "min": 1500.0,
            "max": 2250.0
        },
        {
            "current": 3120.012,
            "min": 1500.0,
            "max": 2250.0
        },
        {
            "current": 3116.546,
            "min": 1500.0,
            "max": 2250.0
        },
        {
            "current": 2250.0,
            "min": 1500.0,
            "max": 2250.0
        },
        {
            "current": 3114.747,
            "min": 1500.0,
            "max": 2250.0
        },
        {
            "current": 3117.839,
            "min": 1500.0,
            "max": 2250.0
        },
        {
            "current": 1500.0,
            "min": 1500.0,
            "max": 2250.0
        },
        {
            "current": 1500.0,
            "min": 1500.0,
            "max": 2250.0
        },
        {
            "current": 2016.501,
            "min": 1500.0,
            "max": 2250.0
        },
        {
            "current": 3129.456,
            "min": 1500.0,
            "max": 2250.0
        },
        {
            "current": 3117.992,
            "min": 1500.0,
            "max": 2250.0
        },
        {
            "current": 3116.638,
            "min": 1500.0,
            "max": 2250.0
        },
        {
            "current": 1500.0,
            "min": 1500.0,
            "max": 2250.0
        },
        {
            "current": 1500.0,
            "min": 1500.0,
            "max": 2250.0
        },
        {
            "current": 3132.503,
            "min": 1500.0,
            "max": 2250.0
        },
        {
            "current": 3128.972,
            "min": 1500.0,
            "max": 2250.0
        },
        {
            "current": 3118.297,
            "min": 1500.0,
            "max": 2250.0
        },
        {
            "current": 3115.585,
            "min": 1500.0,
            "max": 2250.0
        },
        {
            "current": 3116.062,
            "min": 1500.0,
            "max": 2250.0
        },
        {
            "current": 1500.0,
            "min": 1500.0,
            "max": 2250.0
        },
        {
            "current": 1500.0,
            "min": 1500.0,
            "max": 2250.0
        },
        {
            "current": 2250.0,
            "min": 1500.0,
            "max": 2250.0
        },
        {
            "current": 3129.2,
            "min": 1500.0,
            "max": 2250.0
        },
        {
            "current": 3121.236,
            "min": 1500.0,
            "max": 2250.0
        },
        {
            "current": 3120.737,
            "min": 1500.0,
            "max": 2250.0
        },
        {
            "current": 1750.482,
            "min": 1500.0,
            "max": 2250.0
        },
        {
            "current": 1694.721,
            "min": 1500.0,
            "max": 2250.0
        },
        {
            "current": 1500.0,
            "min": 1500.0,
            "max": 2250.0
        },
        {
            "current": 2250.0,
            "min": 1500.0,
            "max": 2250.0
        },
        {
            "current": 2000.0,
            "min": 1500.0,
            "max": 2250.0
        },
        {
            "current": 2000.0,
            "min": 1500.0,
            "max": 2250.0
        },
        {
            "current": 3125.642,
            "min": 1500.0,
            "max": 2250.0
        },
        {
            "current": 1500.0,
            "min": 1500.0,
            "max": 2250.0
        },
        {
            "current": 1500.0,
            "min": 1500.0,
            "max": 2250.0
        },
        {
            "current": 3116.585,
            "min": 1500.0,
            "max": 2250.0
        },
        {
            "current": 2000.0,
            "min": 1500.0,
            "max": 2250.0
        },
        {
            "current": 1500.0,
            "min": 1500.0,
            "max": 2250.0
        },
        {
            "current": 3124.353,
            "min": 1500.0,
            "max": 2250.0
        },
        {
            "current": 3125.662,
            "min": 1500.0,
            "max": 2250.0
        },
        {
            "current": 1500.0,
            "min": 1500.0,
            "max": 2250.0
        },
        {
            "current": 2258.451,
            "min": 1500.0,
            "max": 2250.0
        },
        {
            "current": 3123.189,
            "min": 1500.0,
            "max": 2250.0
        },
        {
            "current": 3119.386,
            "min": 1500.0,
            "max": 2250.0
        },
        {
            "current": 1500.0,
            "min": 1500.0,
            "max": 2250.0
        },
        {
            "current": 3127.695,
            "min": 1500.0,
            "max": 2250.0
        },
        {
            "current": 1500.0,
            "min": 1500.0,
            "max": 2250.0
        },
        {
            "current": 1500.0,
            "min": 1500.0,
            "max": 2250.0
        },
        {
            "current": 3118.907,
            "min": 1500.0,
            "max": 2250.0
        },
        {
            "current": 3124.268,
            "min": 1500.0,
            "max": 2250.0
        },
        {
            "current": 1500.0,
            "min": 1500.0,
            "max": 2250.0
        },
        {
            "current": 1500.0,
            "min": 1500.0,
            "max": 2250.0
        },
        {
            "current": 3117.305,
            "min": 1500.0,
            "max": 2250.0
        },
        {
            "current": 1500.0,
            "min": 1500.0,
            "max": 2250.0
        },
        {
            "current": 3115.659,
            "min": 1500.0,
            "max": 2250.0
        }
    ],
    "disk": {
        "total": 3724.1025772094727,
        "used": 122.15507888793945
    },
    "gpu": "NVIDIA A100-SXM4-40GB",
    "gpu_count": 4,
    "gpu_devices": [
        {
            "name": "NVIDIA A100-SXM4-40GB",
            "memory_total": 42949672960
        },
        {
            "name": "NVIDIA A100-SXM4-40GB",
            "memory_total": 42949672960
        },
        {
            "name": "NVIDIA A100-SXM4-40GB",
            "memory_total": 42949672960
        },
        {
            "name": "NVIDIA A100-SXM4-40GB",
            "memory_total": 42949672960
        }
    ],
    "memory": {
        "total": 251.68415451049805
    }
}
