{
    "os": "Linux-5.13.0-39-generic-x86_64-with-glibc2.31",
    "python": "3.10.10",
    "heartbeatAt": "2023-05-10T19:36:46.418622",
    "startedAt": "2023-05-10T19:36:44.917499",
    "docker": null,
    "cuda": null,
    "args": [
        "--trial-num",
        "3",
        "--exp-group",
        "20230510-2336",
        "--acqf",
        "EIPU-MEMO",
        "--decay-factor",
        "0.99"
    ],
    "state": "running",
    "program": "/home/abdelmajid/workdir/cost-aware-bo/main.py",
    "codePath": "main.py",
    "git": {
        "remote": "https://github.com/ridwan-salau/cost-aware-bo.git",
        "commit": "ee385b56d47047168cf713dbd130ab44d66541cc"
    },
    "email": null,
    "root": "/home/abdelmajid/workdir/cost-aware-bo",
    "host": "gpu-14",
    "username": "abdelmajid",
    "executable": "/home/abdelmajid/miniconda3/envs/tuun/bin/python",
    "cpu_count": 128,
    "cpu_count_logical": 256,
    "cpu_freq": {
        "current": 1647.91255859375,
        "min": 1500.0,
        "max": 2250.0
    },
    "cpu_freq_per_core": [
        {
            "current": 1991.073,
            "min": 1500.0,
            "max": 2250.0
        },
        {
            "current": 1500.0,
            "min": 1500.0,
            "max": 2250.0
        },
        {
            "current": 1500.0,
            "min": 1500.0,
            "max": 2250.0
        },
        {
            "current": 1500.0,
            "min": 1500.0,
            "max": 2250.0
        },
        {
            "current": 1500.0,
            "min": 1500.0,
            "max": 2250.0
        },
        {
            "current": 1500.0,
            "min": 1500.0,
            "max": 2250.0
        },
        {
            "current": 1500.0,
            "min": 1500.0,
            "max": 2250.0
        },
        {
            "current": 1500.0,
            "min": 1500.0,
            "max": 2250.0
        },
        {
            "current": 2250.0,
            "min": 1500.0,
            "max": 2250.0
        },
        {
            "current": 1500.0,
            "min": 1500.0,
            "max": 2250.0
        },
        {
            "current": 1500.0,
            "min": 1500.0,
            "max": 2250.0
        },
        {
            "current": 1500.0,
            "min": 1500.0,
            "max": 2250.0
        },
        {
            "current": 1500.0,
            "min": 1500.0,
            "max": 2250.0
        },
        {
            "current": 1500.0,
            "min": 1500.0,
            "max": 2250.0
        },
        {
            "current": 1500.0,
            "min": 1500.0,
            "max": 2250.0
        },
        {
            "current": 1500.0,
            "min": 1500.0,
            "max": 2250.0
        },
        {
            "current": 1500.0,
            "min": 1500.0,
            "max": 2250.0
        },
        {
            "current": 1500.0,
            "min": 1500.0,
            "max": 2250.0
        },
        {
            "current": 1500.0,
            "min": 1500.0,
            "max": 2250.0
        },
        {
            "current": 1500.0,
            "min": 1500.0,
            "max": 2250.0
        },
        {
            "current": 1500.0,
            "min": 1500.0,
            "max": 2250.0
        },
        {
            "current": 1500.0,
            "min": 1500.0,
            "max": 2250.0
        },
        {
            "current": 1500.0,
            "min": 1500.0,
            "max": 2250.0
        },
        {
            "current": 1993.692,
            "min": 1500.0,
            "max": 2250.0
        },
        {
            "current": 2000.0,
            "min": 1500.0,
            "max": 2250.0
        },
        {
            "current": 2250.0,
            "min": 1500.0,
            "max": 2250.0
        },
        {
            "current": 1500.0,
            "min": 1500.0,
            "max": 2250.0
        },
        {
            "current": 1500.0,
            "min": 1500.0,
            "max": 2250.0
        },
        {
            "current": 1500.0,
            "min": 1500.0,
            "max": 2250.0
        },
        {
            "current": 1500.0,
            "min": 1500.0,
            "max": 2250.0
        },
        {
            "current": 3393.431,
            "min": 1500.0,
            "max": 2250.0
        },
        {
            "current": 1500.0,
            "min": 1500.0,
            "max": 2250.0
        },
        {
            "current": 1500.0,
            "min": 1500.0,
            "max": 2250.0
        },
        {
            "current": 1500.0,
            "min": 1500.0,
            "max": 2250.0
        },
        {
            "current": 1500.0,
            "min": 1500.0,
            "max": 2250.0
        },
        {
            "current": 1500.0,
            "min": 1500.0,
            "max": 2250.0
        },
        {
            "current": 1500.0,
            "min": 1500.0,
            "max": 2250.0
        },
        {
            "current": 1500.0,
            "min": 1500.0,
            "max": 2250.0
        },
        {
            "current": 1500.0,
            "min": 1500.0,
            "max": 2250.0
        },
        {
            "current": 1500.0,
            "min": 1500.0,
            "max": 2250.0
        },
        {
            "current": 1500.0,
            "min": 1500.0,
            "max": 2250.0
        },
        {
            "current": 1500.0,
            "min": 1500.0,
            "max": 2250.0
        },
        {
            "current": 1500.0,
            "min": 1500.0,
            "max": 2250.0
        },
        {
            "current": 1500.0,
            "min": 1500.0,
            "max": 2250.0
        },
        {
            "current": 1500.0,
            "min": 1500.0,
            "max": 2250.0
        },
        {
            "current": 1500.0,
            "min": 1500.0,
            "max": 2250.0
        },
        {
            "current": 1500.0,
            "min": 1500.0,
            "max": 2250.0
        },
        {
            "current": 1500.0,
            "min": 1500.0,
            "max": 2250.0
        },
        {
            "current": 1500.0,
            "min": 1500.0,
            "max": 2250.0
        },
        {
            "current": 1500.0,
            "min": 1500.0,
            "max": 2250.0
        },
        {
            "current": 1500.0,
            "min": 1500.0,
            "max": 2250.0
        },
        {
            "current": 1500.0,
            "min": 1500.0,
            "max": 2250.0
        },
        {
            "current": 1500.0,
            "min": 1500.0,
            "max": 2250.0
        },
        {
            "current": 1500.0,
            "min": 1500.0,
            "max": 2250.0
        },
        {
            "current": 2250.0,
            "min": 1500.0,
            "max": 2250.0
        },
        {
            "current": 2250.0,
            "min": 1500.0,
            "max": 2250.0
        },
        {
            "current": 1500.0,
            "min": 1500.0,
            "max": 2250.0
        },
        {
            "current": 1500.0,
            "min": 1500.0,
            "max": 2250.0
        },
        {
            "current": 1500.0,
            "min": 1500.0,
            "max": 2250.0
        },
        {
            "current": 1500.0,
            "min": 1500.0,
            "max": 2250.0
        },
        {
            "current": 1500.0,
            "min": 1500.0,
            "max": 2250.0
        },
        {
            "current": 2000.0,
            "min": 1500.0,
            "max": 2250.0
        },
        {
            "current": 1500.0,
            "min": 1500.0,
            "max": 2250.0
        },
        {
            "current": 1500.0,
            "min": 1500.0,
            "max": 2250.0
        },
        {
            "current": 1500.0,
            "min": 1500.0,
            "max": 2250.0
        },
        {
            "current": 1500.0,
            "min": 1500.0,
            "max": 2250.0
        },
        {
            "current": 1500.0,
            "min": 1500.0,
            "max": 2250.0
        },
        {
            "current": 1500.0,
            "min": 1500.0,
            "max": 2250.0
        },
        {
            "current": 2250.0,
            "min": 1500.0,
            "max": 2250.0
        },
        {
            "current": 2162.835,
            "min": 1500.0,
            "max": 2250.0
        },
        {
            "current": 1500.0,
            "min": 1500.0,
            "max": 2250.0
        },
        {
            "current": 1500.0,
            "min": 1500.0,
            "max": 2250.0
        },
        {
            "current": 1500.0,
            "min": 1500.0,
            "max": 2250.0
        },
        {
            "current": 1500.0,
            "min": 1500.0,
            "max": 2250.0
        },
        {
            "current": 1500.0,
            "min": 1500.0,
            "max": 2250.0
        },
        {
            "current": 2000.0,
            "min": 1500.0,
            "max": 2250.0
        },
        {
            "current": 3344.649,
            "min": 1500.0,
            "max": 2250.0
        },
        {
            "current": 1500.0,
            "min": 1500.0,
            "max": 2250.0
        },
        {
            "current": 1500.0,
            "min": 1500.0,
            "max": 2250.0
        },
        {
            "current": 1500.0,
            "min": 1500.0,
            "max": 2250.0
        },
        {
            "current": 1500.0,
            "min": 1500.0,
            "max": 2250.0
        },
        {
            "current": 1500.0,
            "min": 1500.0,
            "max": 2250.0
        },
        {
            "current": 1500.0,
            "min": 1500.0,
            "max": 2250.0
        },
        {
            "current": 1500.0,
            "min": 1500.0,
            "max": 2250.0
        },
        {
            "current": 1500.0,
            "min": 1500.0,
            "max": 2250.0
        },
        {
            "current": 1500.0,
            "min": 1500.0,
            "max": 2250.0
        },
        {
            "current": 1500.0,
            "min": 1500.0,
            "max": 2250.0
        },
        {
            "current": 1500.0,
            "min": 1500.0,
            "max": 2250.0
        },
        {
            "current": 1500.0,
            "min": 1500.0,
            "max": 2250.0
        },
        {
            "current": 2250.0,
            "min": 1500.0,
            "max": 2250.0
        },
        {
            "current": 1500.0,
            "min": 1500.0,
            "max": 2250.0
        },
        {
            "current": 1500.0,
            "min": 1500.0,
            "max": 2250.0
        },
        {
            "current": 2250.0,
            "min": 1500.0,
            "max": 2250.0
        },
        {
            "current": 2250.0,
            "min": 1500.0,
            "max": 2250.0
        },
        {
            "current": 1500.0,
            "min": 1500.0,
            "max": 2250.0
        },
        {
            "current": 3349.611,
            "min": 1500.0,
            "max": 2250.0
        },
        {
            "current": 2250.0,
            "min": 1500.0,
            "max": 2250.0
        },
        {
            "current": 1500.0,
            "min": 1500.0,
            "max": 2250.0
        },
        {
            "current": 1500.0,
            "min": 1500.0,
            "max": 2250.0
        },
        {
            "current": 1500.0,
            "min": 1500.0,
            "max": 2250.0
        },
        {
            "current": 1500.0,
            "min": 1500.0,
            "max": 2250.0
        },
        {
            "current": 2000.0,
            "min": 1500.0,
            "max": 2250.0
        },
        {
            "current": 2250.0,
            "min": 1500.0,
            "max": 2250.0
        },
        {
            "current": 1500.0,
            "min": 1500.0,
            "max": 2250.0
        },
        {
            "current": 1500.0,
            "min": 1500.0,
            "max": 2250.0
        },
        {
            "current": 1500.0,
            "min": 1500.0,
            "max": 2250.0
        },
        {
            "current": 1500.0,
            "min": 1500.0,
            "max": 2250.0
        },
        {
            "current": 1500.0,
            "min": 1500.0,
            "max": 2250.0
        },
        {
            "current": 1500.0,
            "min": 1500.0,
            "max": 2250.0
        },
        {
            "current": 1500.0,
            "min": 1500.0,
            "max": 2250.0
        },
        {
            "current": 1500.0,
            "min": 1500.0,
            "max": 2250.0
        },
        {
            "current": 1500.0,
            "min": 1500.0,
            "max": 2250.0
        },
        {
            "current": 1500.0,
            "min": 1500.0,
            "max": 2250.0
        },
        {
            "current": 1500.0,
            "min": 1500.0,
            "max": 2250.0
        },
        {
            "current": 2250.0,
            "min": 1500.0,
            "max": 2250.0
        },
        {
            "current": 2250.0,
            "min": 1500.0,
            "max": 2250.0
        },
        {
            "current": 1500.0,
            "min": 1500.0,
            "max": 2250.0
        },
        {
            "current": 1994.167,
            "min": 1500.0,
            "max": 2250.0
        },
        {
            "current": 1500.0,
            "min": 1500.0,
            "max": 2250.0
        },
        {
            "current": 1500.0,
            "min": 1500.0,
            "max": 2250.0
        },
        {
            "current": 1500.0,
            "min": 1500.0,
            "max": 2250.0
        },
        {
            "current": 1500.0,
            "min": 1500.0,
            "max": 2250.0
        },
        {
            "current": 2250.0,
            "min": 1500.0,
            "max": 2250.0
        },
        {
            "current": 1500.0,
            "min": 1500.0,
            "max": 2250.0
        },
        {
            "current": 1500.0,
            "min": 1500.0,
            "max": 2250.0
        },
        {
            "current": 2250.0,
            "min": 1500.0,
            "max": 2250.0
        },
        {
            "current": 1500.0,
            "min": 1500.0,
            "max": 2250.0
        },
        {
            "current": 2250.0,
            "min": 1500.0,
            "max": 2250.0
        },
        {
            "current": 3373.947,
            "min": 1500.0,
            "max": 2250.0
        },
        {
            "current": 1500.0,
            "min": 1500.0,
            "max": 2250.0
        },
        {
            "current": 1500.0,
            "min": 1500.0,
            "max": 2250.0
        },
        {
            "current": 1500.0,
            "min": 1500.0,
            "max": 2250.0
        },
        {
            "current": 1500.0,
            "min": 1500.0,
            "max": 2250.0
        },
        {
            "current": 1500.0,
            "min": 1500.0,
            "max": 2250.0
        },
        {
            "current": 1500.0,
            "min": 1500.0,
            "max": 2250.0
        },
        {
            "current": 1500.0,
            "min": 1500.0,
            "max": 2250.0
        },
        {
            "current": 1500.0,
            "min": 1500.0,
            "max": 2250.0
        },
        {
            "current": 1500.0,
            "min": 1500.0,
            "max": 2250.0
        },
        {
            "current": 1500.0,
            "min": 1500.0,
            "max": 2250.0
        },
        {
            "current": 1500.0,
            "min": 1500.0,
            "max": 2250.0
        },
        {
            "current": 2000.0,
            "min": 1500.0,
            "max": 2250.0
        },
        {
            "current": 1500.0,
            "min": 1500.0,
            "max": 2250.0
        },
        {
            "current": 1500.0,
            "min": 1500.0,
            "max": 2250.0
        },
        {
            "current": 1500.0,
            "min": 1500.0,
            "max": 2250.0
        },
        {
            "current": 2250.0,
            "min": 1500.0,
            "max": 2250.0
        },
        {
            "current": 1500.0,
            "min": 1500.0,
            "max": 2250.0
        },
        {
            "current": 1500.0,
            "min": 1500.0,
            "max": 2250.0
        },
        {
            "current": 1500.0,
            "min": 1500.0,
            "max": 2250.0
        },
        {
            "current": 1500.0,
            "min": 1500.0,
            "max": 2250.0
        },
        {
            "current": 1500.0,
            "min": 1500.0,
            "max": 2250.0
        },
        {
            "current": 1500.0,
            "min": 1500.0,
            "max": 2250.0
        },
        {
            "current": 1500.0,
            "min": 1500.0,
            "max": 2250.0
        },
        {
            "current": 1500.0,
            "min": 1500.0,
            "max": 2250.0
        },
        {
            "current": 1500.0,
            "min": 1500.0,
            "max": 2250.0
        },
        {
            "current": 1500.0,
            "min": 1500.0,
            "max": 2250.0
        },
        {
            "current": 1500.0,
            "min": 1500.0,
            "max": 2250.0
        },
        {
            "current": 1500.0,
            "min": 1500.0,
            "max": 2250.0
        },
        {
            "current": 1500.0,
            "min": 1500.0,
            "max": 2250.0
        },
        {
            "current": 1500.0,
            "min": 1500.0,
            "max": 2250.0
        },
        {
            "current": 1500.0,
            "min": 1500.0,
            "max": 2250.0
        },
        {
            "current": 2250.0,
            "min": 1500.0,
            "max": 2250.0
        },
        {
            "current": 1500.0,
            "min": 1500.0,
            "max": 2250.0
        },
        {
            "current": 1500.0,
            "min": 1500.0,
            "max": 2250.0
        },
        {
            "current": 2000.0,
            "min": 1500.0,
            "max": 2250.0
        },
        {
            "current": 1500.0,
            "min": 1500.0,
            "max": 2250.0
        },
        {
            "current": 2000.0,
            "min": 1500.0,
            "max": 2250.0
        },
        {
            "current": 1500.0,
            "min": 1500.0,
            "max": 2250.0
        },
        {
            "current": 1500.0,
            "min": 1500.0,
            "max": 2250.0
        },
        {
            "current": 1500.0,
            "min": 1500.0,
            "max": 2250.0
        },
        {
            "current": 1500.0,
            "min": 1500.0,
            "max": 2250.0
        },
        {
            "current": 1500.0,
            "min": 1500.0,
            "max": 2250.0
        },
        {
            "current": 1500.0,
            "min": 1500.0,
            "max": 2250.0
        },
        {
            "current": 1500.0,
            "min": 1500.0,
            "max": 2250.0
        },
        {
            "current": 1500.0,
            "min": 1500.0,
            "max": 2250.0
        },
        {
            "current": 1500.0,
            "min": 1500.0,
            "max": 2250.0
        },
        {
            "current": 1500.0,
            "min": 1500.0,
            "max": 2250.0
        },
        {
            "current": 1500.0,
            "min": 1500.0,
            "max": 2250.0
        },
        {
            "current": 1500.0,
            "min": 1500.0,
            "max": 2250.0
        },
        {
            "current": 1500.0,
            "min": 1500.0,
            "max": 2250.0
        },
        {
            "current": 1500.0,
            "min": 1500.0,
            "max": 2250.0
        },
        {
            "current": 2795.595,
            "min": 1500.0,
            "max": 2250.0
        },
        {
            "current": 1500.0,
            "min": 1500.0,
            "max": 2250.0
        },
        {
            "current": 2250.0,
            "min": 1500.0,
            "max": 2250.0
        },
        {
            "current": 2250.0,
            "min": 1500.0,
            "max": 2250.0
        },
        {
            "current": 1500.0,
            "min": 1500.0,
            "max": 2250.0
        },
        {
            "current": 1500.0,
            "min": 1500.0,
            "max": 2250.0
        },
        {
            "current": 3373.833,
            "min": 1500.0,
            "max": 2250.0
        },
        {
            "current": 1500.0,
            "min": 1500.0,
            "max": 2250.0
        },
        {
            "current": 1500.0,
            "min": 1500.0,
            "max": 2250.0
        },
        {
            "current": 1500.0,
            "min": 1500.0,
            "max": 2250.0
        },
        {
            "current": 1500.0,
            "min": 1500.0,
            "max": 2250.0
        },
        {
            "current": 1500.0,
            "min": 1500.0,
            "max": 2250.0
        },
        {
            "current": 1500.0,
            "min": 1500.0,
            "max": 2250.0
        },
        {
            "current": 2250.0,
            "min": 1500.0,
            "max": 2250.0
        },
        {
            "current": 1579.093,
            "min": 1500.0,
            "max": 2250.0
        },
        {
            "current": 1500.0,
            "min": 1500.0,
            "max": 2250.0
        },
        {
            "current": 1500.0,
            "min": 1500.0,
            "max": 2250.0
        },
        {
            "current": 1500.0,
            "min": 1500.0,
            "max": 2250.0
        },
        {
            "current": 1500.0,
            "min": 1500.0,
            "max": 2250.0
        },
        {
            "current": 1500.0,
            "min": 1500.0,
            "max": 2250.0
        },
        {
            "current": 1500.0,
            "min": 1500.0,
            "max": 2250.0
        },
        {
            "current": 1500.0,
            "min": 1500.0,
            "max": 2250.0
        },
        {
            "current": 3345.75,
            "min": 1500.0,
            "max": 2250.0
        },
        {
            "current": 1500.0,
            "min": 1500.0,
            "max": 2250.0
        },
        {
            "current": 1500.0,
            "min": 1500.0,
            "max": 2250.0
        },
        {
            "current": 1500.0,
            "min": 1500.0,
            "max": 2250.0
        },
        {
            "current": 3347.711,
            "min": 1500.0,
            "max": 2250.0
        },
        {
            "current": 3347.609,
            "min": 1500.0,
            "max": 2250.0
        },
        {
            "current": 1500.0,
            "min": 1500.0,
            "max": 2250.0
        },
        {
            "current": 1500.0,
            "min": 1500.0,
            "max": 2250.0
        },
        {
            "current": 1497.69,
            "min": 1500.0,
            "max": 2250.0
        },
        {
            "current": 1500.0,
            "min": 1500.0,
            "max": 2250.0
        },
        {
            "current": 2250.0,
            "min": 1500.0,
            "max": 2250.0
        },
        {
            "current": 1500.0,
            "min": 1500.0,
            "max": 2250.0
        },
        {
            "current": 1500.0,
            "min": 1500.0,
            "max": 2250.0
        },
        {
            "current": 2250.0,
            "min": 1500.0,
            "max": 2250.0
        },
        {
            "current": 1500.0,
            "min": 1500.0,
            "max": 2250.0
        },
        {
            "current": 2250.0,
            "min": 1500.0,
            "max": 2250.0
        },
        {
            "current": 1500.0,
            "min": 1500.0,
            "max": 2250.0
        },
        {
            "current": 2250.0,
            "min": 1500.0,
            "max": 2250.0
        },
        {
            "current": 1500.0,
            "min": 1500.0,
            "max": 2250.0
        },
        {
            "current": 1500.0,
            "min": 1500.0,
            "max": 2250.0
        },
        {
            "current": 1500.0,
            "min": 1500.0,
            "max": 2250.0
        },
        {
            "current": 2250.0,
            "min": 1500.0,
            "max": 2250.0
        },
        {
            "current": 1500.0,
            "min": 1500.0,
            "max": 2250.0
        },
        {
            "current": 1500.0,
            "min": 1500.0,
            "max": 2250.0
        },
        {
            "current": 1500.0,
            "min": 1500.0,
            "max": 2250.0
        },
        {
            "current": 2250.0,
            "min": 1500.0,
            "max": 2250.0
        },
        {
            "current": 1500.0,
            "min": 1500.0,
            "max": 2250.0
        },
        {
            "current": 1500.0,
            "min": 1500.0,
            "max": 2250.0
        },
        {
            "current": 1500.0,
            "min": 1500.0,
            "max": 2250.0
        },
        {
            "current": 1500.0,
            "min": 1500.0,
            "max": 2250.0
        },
        {
            "current": 1500.0,
            "min": 1500.0,
            "max": 2250.0
        },
        {
            "current": 1500.0,
            "min": 1500.0,
            "max": 2250.0
        },
        {
            "current": 1500.0,
            "min": 1500.0,
            "max": 2250.0
        },
        {
            "current": 1500.0,
            "min": 1500.0,
            "max": 2250.0
        },
        {
            "current": 1500.0,
            "min": 1500.0,
            "max": 2250.0
        },
        {
            "current": 1500.0,
            "min": 1500.0,
            "max": 2250.0
        },
        {
            "current": 2250.0,
            "min": 1500.0,
            "max": 2250.0
        },
        {
            "current": 1500.0,
            "min": 1500.0,
            "max": 2250.0
        },
        {
            "current": 1500.0,
            "min": 1500.0,
            "max": 2250.0
        },
        {
            "current": 1500.0,
            "min": 1500.0,
            "max": 2250.0
        },
        {
            "current": 1500.0,
            "min": 1500.0,
            "max": 2250.0
        },
        {
            "current": 2000.0,
            "min": 1500.0,
            "max": 2250.0
        },
        {
            "current": 1500.0,
            "min": 1500.0,
            "max": 2250.0
        },
        {
            "current": 1500.0,
            "min": 1500.0,
            "max": 2250.0
        },
        {
            "current": 1500.0,
            "min": 1500.0,
            "max": 2250.0
        },
        {
            "current": 2250.0,
            "min": 1500.0,
            "max": 2250.0
        },
        {
            "current": 1500.0,
            "min": 1500.0,
            "max": 2250.0
        },
        {
            "current": 2250.0,
            "min": 1500.0,
            "max": 2250.0
        },
        {
            "current": 1500.0,
            "min": 1500.0,
            "max": 2250.0
        },
        {
            "current": 1500.0,
            "min": 1500.0,
            "max": 2250.0
        },
        {
            "current": 1500.0,
            "min": 1500.0,
            "max": 2250.0
        },
        {
            "current": 1500.0,
            "min": 1500.0,
            "max": 2250.0
        },
        {
            "current": 1500.0,
            "min": 1500.0,
            "max": 2250.0
        },
        {
            "current": 3346.904,
            "min": 1500.0,
            "max": 2250.0
        }
    ],
    "disk": {
        "total": 3724.1025772094727,
        "used": 129.2969970703125
    },
    "gpu": "NVIDIA A100-SXM4-40GB",
    "gpu_count": 4,
    "gpu_devices": [
        {
            "name": "NVIDIA A100-SXM4-40GB",
            "memory_total": 42949672960
        },
        {
            "name": "NVIDIA A100-SXM4-40GB",
            "memory_total": 42949672960
        },
        {
            "name": "NVIDIA A100-SXM4-40GB",
            "memory_total": 42949672960
        },
        {
            "name": "NVIDIA A100-SXM4-40GB",
            "memory_total": 42949672960
        }
    ],
    "memory": {
        "total": 251.68415451049805
    }
}
