{
    "os": "Linux-5.13.0-39-generic-x86_64-with-glibc2.31",
    "python": "3.10.10",
    "heartbeatAt": "2023-05-05T20:56:57.969867",
    "startedAt": "2023-05-05T20:56:57.013485",
    "docker": null,
    "cuda": null,
    "args": [
        "--trial-num",
        "3",
        "--exp-group",
        "20230506-0056",
        "--acqf",
        "EI",
        "--decay-factor",
        "0"
    ],
    "state": "running",
    "program": "/home/abdelmajid/workdir/cost-aware-bo/main.py",
    "codePath": "main.py",
    "git": {
        "remote": "https://github.com/ridwan-salau/cost-aware-bo.git",
        "commit": "ee385b56d47047168cf713dbd130ab44d66541cc"
    },
    "email": null,
    "root": "/home/abdelmajid/workdir/cost-aware-bo",
    "host": "gpu-14",
    "username": "abdelmajid",
    "executable": "/home/abdelmajid/miniconda3/envs/tuun/bin/python",
    "cpu_count": 128,
    "cpu_count_logical": 256,
    "cpu_freq": {
        "current": 2526.0260624999987,
        "min": 1500.0,
        "max": 2250.0
    },
    "cpu_freq_per_core": [
        {
            "current": 3240.581,
            "min": 1500.0,
            "max": 2250.0
        },
        {
            "current": 2000.0,
            "min": 1500.0,
            "max": 2250.0
        },
        {
            "current": 2000.0,
            "min": 1500.0,
            "max": 2250.0
        },
        {
            "current": 2250.0,
            "min": 1500.0,
            "max": 2250.0
        },
        {
            "current": 1500.0,
            "min": 1500.0,
            "max": 2250.0
        },
        {
            "current": 1500.0,
            "min": 1500.0,
            "max": 2250.0
        },
        {
            "current": 2250.0,
            "min": 1500.0,
            "max": 2250.0
        },
        {
            "current": 2250.0,
            "min": 1500.0,
            "max": 2250.0
        },
        {
            "current": 2250.0,
            "min": 1500.0,
            "max": 2250.0
        },
        {
            "current": 2250.0,
            "min": 1500.0,
            "max": 2250.0
        },
        {
            "current": 2000.0,
            "min": 1500.0,
            "max": 2250.0
        },
        {
            "current": 1500.0,
            "min": 1500.0,
            "max": 2250.0
        },
        {
            "current": 2250.0,
            "min": 1500.0,
            "max": 2250.0
        },
        {
            "current": 2250.0,
            "min": 1500.0,
            "max": 2250.0
        },
        {
            "current": 2250.0,
            "min": 1500.0,
            "max": 2250.0
        },
        {
            "current": 2250.0,
            "min": 1500.0,
            "max": 2250.0
        },
        {
            "current": 1500.0,
            "min": 1500.0,
            "max": 2250.0
        },
        {
            "current": 2250.0,
            "min": 1500.0,
            "max": 2250.0
        },
        {
            "current": 2250.0,
            "min": 1500.0,
            "max": 2250.0
        },
        {
            "current": 2250.0,
            "min": 1500.0,
            "max": 2250.0
        },
        {
            "current": 1500.0,
            "min": 1500.0,
            "max": 2250.0
        },
        {
            "current": 1500.0,
            "min": 1500.0,
            "max": 2250.0
        },
        {
            "current": 1500.0,
            "min": 1500.0,
            "max": 2250.0
        },
        {
            "current": 2250.0,
            "min": 1500.0,
            "max": 2250.0
        },
        {
            "current": 2250.0,
            "min": 1500.0,
            "max": 2250.0
        },
        {
            "current": 2250.0,
            "min": 1500.0,
            "max": 2250.0
        },
        {
            "current": 2000.0,
            "min": 1500.0,
            "max": 2250.0
        },
        {
            "current": 2250.0,
            "min": 1500.0,
            "max": 2250.0
        },
        {
            "current": 1500.0,
            "min": 1500.0,
            "max": 2250.0
        },
        {
            "current": 2250.0,
            "min": 1500.0,
            "max": 2250.0
        },
        {
            "current": 2000.0,
            "min": 1500.0,
            "max": 2250.0
        },
        {
            "current": 2250.0,
            "min": 1500.0,
            "max": 2250.0
        },
        {
            "current": 2250.0,
            "min": 1500.0,
            "max": 2250.0
        },
        {
            "current": 2250.0,
            "min": 1500.0,
            "max": 2250.0
        },
        {
            "current": 2250.0,
            "min": 1500.0,
            "max": 2250.0
        },
        {
            "current": 2250.0,
            "min": 1500.0,
            "max": 2250.0
        },
        {
            "current": 2250.0,
            "min": 1500.0,
            "max": 2250.0
        },
        {
            "current": 1500.0,
            "min": 1500.0,
            "max": 2250.0
        },
        {
            "current": 2250.0,
            "min": 1500.0,
            "max": 2250.0
        },
        {
            "current": 2250.0,
            "min": 1500.0,
            "max": 2250.0
        },
        {
            "current": 2250.0,
            "min": 1500.0,
            "max": 2250.0
        },
        {
            "current": 2250.0,
            "min": 1500.0,
            "max": 2250.0
        },
        {
            "current": 2250.0,
            "min": 1500.0,
            "max": 2250.0
        },
        {
            "current": 2250.0,
            "min": 1500.0,
            "max": 2250.0
        },
        {
            "current": 1500.0,
            "min": 1500.0,
            "max": 2250.0
        },
        {
            "current": 2250.0,
            "min": 1500.0,
            "max": 2250.0
        },
        {
            "current": 2250.0,
            "min": 1500.0,
            "max": 2250.0
        },
        {
            "current": 2250.0,
            "min": 1500.0,
            "max": 2250.0
        },
        {
            "current": 2250.0,
            "min": 1500.0,
            "max": 2250.0
        },
        {
            "current": 2250.0,
            "min": 1500.0,
            "max": 2250.0
        },
        {
            "current": 1500.0,
            "min": 1500.0,
            "max": 2250.0
        },
        {
            "current": 2250.0,
            "min": 1500.0,
            "max": 2250.0
        },
        {
            "current": 2250.0,
            "min": 1500.0,
            "max": 2250.0
        },
        {
            "current": 1500.0,
            "min": 1500.0,
            "max": 2250.0
        },
        {
            "current": 2250.0,
            "min": 1500.0,
            "max": 2250.0
        },
        {
            "current": 1500.0,
            "min": 1500.0,
            "max": 2250.0
        },
        {
            "current": 2250.0,
            "min": 1500.0,
            "max": 2250.0
        },
        {
            "current": 2000.0,
            "min": 1500.0,
            "max": 2250.0
        },
        {
            "current": 2832.179,
            "min": 1500.0,
            "max": 2250.0
        },
        {
            "current": 2250.0,
            "min": 1500.0,
            "max": 2250.0
        },
        {
            "current": 2250.0,
            "min": 1500.0,
            "max": 2250.0
        },
        {
            "current": 2250.0,
            "min": 1500.0,
            "max": 2250.0
        },
        {
            "current": 2250.0,
            "min": 1500.0,
            "max": 2250.0
        },
        {
            "current": 2000.0,
            "min": 1500.0,
            "max": 2250.0
        },
        {
            "current": 1500.0,
            "min": 1500.0,
            "max": 2250.0
        },
        {
            "current": 2250.0,
            "min": 1500.0,
            "max": 2250.0
        },
        {
            "current": 1500.0,
            "min": 1500.0,
            "max": 2250.0
        },
        {
            "current": 1500.0,
            "min": 1500.0,
            "max": 2250.0
        },
        {
            "current": 1500.0,
            "min": 1500.0,
            "max": 2250.0
        },
        {
            "current": 1857.508,
            "min": 1500.0,
            "max": 2250.0
        },
        {
            "current": 2250.0,
            "min": 1500.0,
            "max": 2250.0
        },
        {
            "current": 2250.0,
            "min": 1500.0,
            "max": 2250.0
        },
        {
            "current": 2250.0,
            "min": 1500.0,
            "max": 2250.0
        },
        {
            "current": 1500.0,
            "min": 1500.0,
            "max": 2250.0
        },
        {
            "current": 1500.0,
            "min": 1500.0,
            "max": 2250.0
        },
        {
            "current": 3249.367,
            "min": 1500.0,
            "max": 2250.0
        },
        {
            "current": 2250.0,
            "min": 1500.0,
            "max": 2250.0
        },
        {
            "current": 1500.0,
            "min": 1500.0,
            "max": 2250.0
        },
        {
            "current": 1500.0,
            "min": 1500.0,
            "max": 2250.0
        },
        {
            "current": 1500.0,
            "min": 1500.0,
            "max": 2250.0
        },
        {
            "current": 1500.0,
            "min": 1500.0,
            "max": 2250.0
        },
        {
            "current": 1500.0,
            "min": 1500.0,
            "max": 2250.0
        },
        {
            "current": 3108.337,
            "min": 1500.0,
            "max": 2250.0
        },
        {
            "current": 2250.0,
            "min": 1500.0,
            "max": 2250.0
        },
        {
            "current": 1500.0,
            "min": 1500.0,
            "max": 2250.0
        },
        {
            "current": 2250.0,
            "min": 1500.0,
            "max": 2250.0
        },
        {
            "current": 3249.983,
            "min": 1500.0,
            "max": 2250.0
        },
        {
            "current": 1500.0,
            "min": 1500.0,
            "max": 2250.0
        },
        {
            "current": 2250.0,
            "min": 1500.0,
            "max": 2250.0
        },
        {
            "current": 1500.0,
            "min": 1500.0,
            "max": 2250.0
        },
        {
            "current": 1500.0,
            "min": 1500.0,
            "max": 2250.0
        },
        {
            "current": 2250.0,
            "min": 1500.0,
            "max": 2250.0
        },
        {
            "current": 2914.711,
            "min": 1500.0,
            "max": 2250.0
        },
        {
            "current": 1500.0,
            "min": 1500.0,
            "max": 2250.0
        },
        {
            "current": 1500.0,
            "min": 1500.0,
            "max": 2250.0
        },
        {
            "current": 1500.0,
            "min": 1500.0,
            "max": 2250.0
        },
        {
            "current": 1464.063,
            "min": 1500.0,
            "max": 2250.0
        },
        {
            "current": 2373.287,
            "min": 1500.0,
            "max": 2250.0
        },
        {
            "current": 1500.0,
            "min": 1500.0,
            "max": 2250.0
        },
        {
            "current": 1500.0,
            "min": 1500.0,
            "max": 2250.0
        },
        {
            "current": 2250.0,
            "min": 1500.0,
            "max": 2250.0
        },
        {
            "current": 1500.0,
            "min": 1500.0,
            "max": 2250.0
        },
        {
            "current": 2250.0,
            "min": 1500.0,
            "max": 2250.0
        },
        {
            "current": 1500.0,
            "min": 1500.0,
            "max": 2250.0
        },
        {
            "current": 1500.0,
            "min": 1500.0,
            "max": 2250.0
        },
        {
            "current": 2250.0,
            "min": 1500.0,
            "max": 2250.0
        },
        {
            "current": 2000.0,
            "min": 1500.0,
            "max": 2250.0
        },
        {
            "current": 2250.0,
            "min": 1500.0,
            "max": 2250.0
        },
        {
            "current": 3245.687,
            "min": 1500.0,
            "max": 2250.0
        },
        {
            "current": 2250.0,
            "min": 1500.0,
            "max": 2250.0
        },
        {
            "current": 2250.0,
            "min": 1500.0,
            "max": 2250.0
        },
        {
            "current": 2250.0,
            "min": 1500.0,
            "max": 2250.0
        },
        {
            "current": 3248.055,
            "min": 1500.0,
            "max": 2250.0
        },
        {
            "current": 2250.0,
            "min": 1500.0,
            "max": 2250.0
        },
        {
            "current": 2250.0,
            "min": 1500.0,
            "max": 2250.0
        },
        {
            "current": 1500.0,
            "min": 1500.0,
            "max": 2250.0
        },
        {
            "current": 2250.0,
            "min": 1500.0,
            "max": 2250.0
        },
        {
            "current": 2250.0,
            "min": 1500.0,
            "max": 2250.0
        },
        {
            "current": 2250.0,
            "min": 1500.0,
            "max": 2250.0
        },
        {
            "current": 3249.991,
            "min": 1500.0,
            "max": 2250.0
        },
        {
            "current": 2250.0,
            "min": 1500.0,
            "max": 2250.0
        },
        {
            "current": 1500.0,
            "min": 1500.0,
            "max": 2250.0
        },
        {
            "current": 2250.0,
            "min": 1500.0,
            "max": 2250.0
        },
        {
            "current": 3054.098,
            "min": 1500.0,
            "max": 2250.0
        },
        {
            "current": 2250.0,
            "min": 1500.0,
            "max": 2250.0
        },
        {
            "current": 2250.0,
            "min": 1500.0,
            "max": 2250.0
        },
        {
            "current": 3247.552,
            "min": 1500.0,
            "max": 2250.0
        },
        {
            "current": 1500.0,
            "min": 1500.0,
            "max": 2250.0
        },
        {
            "current": 1500.0,
            "min": 1500.0,
            "max": 2250.0
        },
        {
            "current": 1500.0,
            "min": 1500.0,
            "max": 2250.0
        },
        {
            "current": 2250.0,
            "min": 1500.0,
            "max": 2250.0
        },
        {
            "current": 2250.0,
            "min": 1500.0,
            "max": 2250.0
        },
        {
            "current": 2250.0,
            "min": 1500.0,
            "max": 2250.0
        },
        {
            "current": 2000.0,
            "min": 1500.0,
            "max": 2250.0
        },
        {
            "current": 2250.0,
            "min": 1500.0,
            "max": 2250.0
        },
        {
            "current": 1500.0,
            "min": 1500.0,
            "max": 2250.0
        },
        {
            "current": 1500.0,
            "min": 1500.0,
            "max": 2250.0
        },
        {
            "current": 1500.0,
            "min": 1500.0,
            "max": 2250.0
        },
        {
            "current": 2250.0,
            "min": 1500.0,
            "max": 2250.0
        },
        {
            "current": 2250.0,
            "min": 1500.0,
            "max": 2250.0
        },
        {
            "current": 2250.0,
            "min": 1500.0,
            "max": 2250.0
        },
        {
            "current": 2250.0,
            "min": 1500.0,
            "max": 2250.0
        },
        {
            "current": 2250.0,
            "min": 1500.0,
            "max": 2250.0
        },
        {
            "current": 1500.0,
            "min": 1500.0,
            "max": 2250.0
        },
        {
            "current": 2250.0,
            "min": 1500.0,
            "max": 2250.0
        },
        {
            "current": 1500.0,
            "min": 1500.0,
            "max": 2250.0
        },
        {
            "current": 2250.0,
            "min": 1500.0,
            "max": 2250.0
        },
        {
            "current": 2250.0,
            "min": 1500.0,
            "max": 2250.0
        },
        {
            "current": 3288.647,
            "min": 1500.0,
            "max": 2250.0
        },
        {
            "current": 2250.0,
            "min": 1500.0,
            "max": 2250.0
        },
        {
            "current": 1500.0,
            "min": 1500.0,
            "max": 2250.0
        },
        {
            "current": 1500.0,
            "min": 1500.0,
            "max": 2250.0
        },
        {
            "current": 2250.0,
            "min": 1500.0,
            "max": 2250.0
        },
        {
            "current": 2250.0,
            "min": 1500.0,
            "max": 2250.0
        },
        {
            "current": 2250.0,
            "min": 1500.0,
            "max": 2250.0
        },
        {
            "current": 2250.0,
            "min": 1500.0,
            "max": 2250.0
        },
        {
            "current": 2250.0,
            "min": 1500.0,
            "max": 2250.0
        },
        {
            "current": 2250.0,
            "min": 1500.0,
            "max": 2250.0
        },
        {
            "current": 1500.0,
            "min": 1500.0,
            "max": 2250.0
        },
        {
            "current": 2000.0,
            "min": 1500.0,
            "max": 2250.0
        },
        {
            "current": 2000.0,
            "min": 1500.0,
            "max": 2250.0
        },
        {
            "current": 1500.0,
            "min": 1500.0,
            "max": 2250.0
        },
        {
            "current": 1500.0,
            "min": 1500.0,
            "max": 2250.0
        },
        {
            "current": 2000.0,
            "min": 1500.0,
            "max": 2250.0
        },
        {
            "current": 1500.0,
            "min": 1500.0,
            "max": 2250.0
        },
        {
            "current": 2250.0,
            "min": 1500.0,
            "max": 2250.0
        },
        {
            "current": 2250.0,
            "min": 1500.0,
            "max": 2250.0
        },
        {
            "current": 1500.0,
            "min": 1500.0,
            "max": 2250.0
        },
        {
            "current": 3287.127,
            "min": 1500.0,
            "max": 2250.0
        },
        {
            "current": 2250.0,
            "min": 1500.0,
            "max": 2250.0
        },
        {
            "current": 2000.0,
            "min": 1500.0,
            "max": 2250.0
        },
        {
            "current": 2250.0,
            "min": 1500.0,
            "max": 2250.0
        },
        {
            "current": 2250.0,
            "min": 1500.0,
            "max": 2250.0
        },
        {
            "current": 1500.0,
            "min": 1500.0,
            "max": 2250.0
        },
        {
            "current": 2000.0,
            "min": 1500.0,
            "max": 2250.0
        },
        {
            "current": 2250.0,
            "min": 1500.0,
            "max": 2250.0
        },
        {
            "current": 2250.0,
            "min": 1500.0,
            "max": 2250.0
        },
        {
            "current": 2250.0,
            "min": 1500.0,
            "max": 2250.0
        },
        {
            "current": 2250.0,
            "min": 1500.0,
            "max": 2250.0
        },
        {
            "current": 2250.0,
            "min": 1500.0,
            "max": 2250.0
        },
        {
            "current": 2250.0,
            "min": 1500.0,
            "max": 2250.0
        },
        {
            "current": 2250.0,
            "min": 1500.0,
            "max": 2250.0
        },
        {
            "current": 1500.0,
            "min": 1500.0,
            "max": 2250.0
        },
        {
            "current": 2250.0,
            "min": 1500.0,
            "max": 2250.0
        },
        {
            "current": 1500.0,
            "min": 1500.0,
            "max": 2250.0
        },
        {
            "current": 1500.0,
            "min": 1500.0,
            "max": 2250.0
        },
        {
            "current": 1500.0,
            "min": 1500.0,
            "max": 2250.0
        },
        {
            "current": 1500.0,
            "min": 1500.0,
            "max": 2250.0
        },
        {
            "current": 2250.0,
            "min": 1500.0,
            "max": 2250.0
        },
        {
            "current": 2250.0,
            "min": 1500.0,
            "max": 2250.0
        },
        {
            "current": 2250.0,
            "min": 1500.0,
            "max": 2250.0
        },
        {
            "current": 1500.0,
            "min": 1500.0,
            "max": 2250.0
        },
        {
            "current": 3247.014,
            "min": 1500.0,
            "max": 2250.0
        },
        {
            "current": 2250.0,
            "min": 1500.0,
            "max": 2250.0
        },
        {
            "current": 2250.0,
            "min": 1500.0,
            "max": 2250.0
        },
        {
            "current": 3245.215,
            "min": 1500.0,
            "max": 2250.0
        },
        {
            "current": 3223.439,
            "min": 1500.0,
            "max": 2250.0
        },
        {
            "current": 1856.669,
            "min": 1500.0,
            "max": 2250.0
        },
        {
            "current": 1500.0,
            "min": 1500.0,
            "max": 2250.0
        },
        {
            "current": 2631.251,
            "min": 1500.0,
            "max": 2250.0
        },
        {
            "current": 1500.0,
            "min": 1500.0,
            "max": 2250.0
        },
        {
            "current": 2250.0,
            "min": 1500.0,
            "max": 2250.0
        },
        {
            "current": 1855.808,
            "min": 1500.0,
            "max": 2250.0
        },
        {
            "current": 2250.0,
            "min": 1500.0,
            "max": 2250.0
        },
        {
            "current": 1500.0,
            "min": 1500.0,
            "max": 2250.0
        },
        {
            "current": 3173.151,
            "min": 1500.0,
            "max": 2250.0
        },
        {
            "current": 3247.196,
            "min": 1500.0,
            "max": 2250.0
        },
        {
            "current": 2925.951,
            "min": 1500.0,
            "max": 2250.0
        },
        {
            "current": 2250.0,
            "min": 1500.0,
            "max": 2250.0
        },
        {
            "current": 2250.0,
            "min": 1500.0,
            "max": 2250.0
        },
        {
            "current": 2000.0,
            "min": 1500.0,
            "max": 2250.0
        },
        {
            "current": 3029.21,
            "min": 1500.0,
            "max": 2250.0
        },
        {
            "current": 3108.942,
            "min": 1500.0,
            "max": 2250.0
        },
        {
            "current": 1500.0,
            "min": 1500.0,
            "max": 2250.0
        },
        {
            "current": 2250.0,
            "min": 1500.0,
            "max": 2250.0
        },
        {
            "current": 2538.869,
            "min": 1500.0,
            "max": 2250.0
        },
        {
            "current": 1500.0,
            "min": 1500.0,
            "max": 2250.0
        },
        {
            "current": 3247.147,
            "min": 1500.0,
            "max": 2250.0
        },
        {
            "current": 2547.718,
            "min": 1500.0,
            "max": 2250.0
        },
        {
            "current": 3246.557,
            "min": 1500.0,
            "max": 2250.0
        },
        {
            "current": 1675.796,
            "min": 1500.0,
            "max": 2250.0
        },
        {
            "current": 2000.0,
            "min": 1500.0,
            "max": 2250.0
        },
        {
            "current": 1500.0,
            "min": 1500.0,
            "max": 2250.0
        },
        {
            "current": 2250.0,
            "min": 1500.0,
            "max": 2250.0
        },
        {
            "current": 1500.0,
            "min": 1500.0,
            "max": 2250.0
        },
        {
            "current": 2250.0,
            "min": 1500.0,
            "max": 2250.0
        },
        {
            "current": 1500.0,
            "min": 1500.0,
            "max": 2250.0
        },
        {
            "current": 1500.0,
            "min": 1500.0,
            "max": 2250.0
        },
        {
            "current": 3249.173,
            "min": 1500.0,
            "max": 2250.0
        },
        {
            "current": 2250.0,
            "min": 1500.0,
            "max": 2250.0
        },
        {
            "current": 3248.066,
            "min": 1500.0,
            "max": 2250.0
        },
        {
            "current": 1500.0,
            "min": 1500.0,
            "max": 2250.0
        },
        {
            "current": 3246.999,
            "min": 1500.0,
            "max": 2250.0
        },
        {
            "current": 2250.0,
            "min": 1500.0,
            "max": 2250.0
        },
        {
            "current": 2976.071,
            "min": 1500.0,
            "max": 2250.0
        },
        {
            "current": 3247.214,
            "min": 1500.0,
            "max": 2250.0
        },
        {
            "current": 2250.0,
            "min": 1500.0,
            "max": 2250.0
        },
        {
            "current": 2250.0,
            "min": 1500.0,
            "max": 2250.0
        },
        {
            "current": 3235.434,
            "min": 1500.0,
            "max": 2250.0
        },
        {
            "current": 3248.029,
            "min": 1500.0,
            "max": 2250.0
        },
        {
            "current": 2250.0,
            "min": 1500.0,
            "max": 2250.0
        },
        {
            "current": 3245.532,
            "min": 1500.0,
            "max": 2250.0
        },
        {
            "current": 3246.726,
            "min": 1500.0,
            "max": 2250.0
        },
        {
            "current": 2970.059,
            "min": 1500.0,
            "max": 2250.0
        },
        {
            "current": 3246.948,
            "min": 1500.0,
            "max": 2250.0
        },
        {
            "current": 3248.931,
            "min": 1500.0,
            "max": 2250.0
        },
        {
            "current": 1500.0,
            "min": 1500.0,
            "max": 2250.0
        },
        {
            "current": 2250.0,
            "min": 1500.0,
            "max": 2250.0
        },
        {
            "current": 1500.0,
            "min": 1500.0,
            "max": 2250.0
        },
        {
            "current": 3191.549,
            "min": 1500.0,
            "max": 2250.0
        },
        {
            "current": 3246.451,
            "min": 1500.0,
            "max": 2250.0
        },
        {
            "current": 1500.0,
            "min": 1500.0,
            "max": 2250.0
        },
        {
            "current": 3246.681,
            "min": 1500.0,
            "max": 2250.0
        },
        {
            "current": 2818.535,
            "min": 1500.0,
            "max": 2250.0
        },
        {
            "current": 1500.0,
            "min": 1500.0,
            "max": 2250.0
        },
        {
            "current": 3246.782,
            "min": 1500.0,
            "max": 2250.0
        }
    ],
    "disk": {
        "total": 3724.1025772094727,
        "used": 122.16592407226562
    },
    "gpu": "NVIDIA A100-SXM4-40GB",
    "gpu_count": 4,
    "gpu_devices": [
        {
            "name": "NVIDIA A100-SXM4-40GB",
            "memory_total": 42949672960
        },
        {
            "name": "NVIDIA A100-SXM4-40GB",
            "memory_total": 42949672960
        },
        {
            "name": "NVIDIA A100-SXM4-40GB",
            "memory_total": 42949672960
        },
        {
            "name": "NVIDIA A100-SXM4-40GB",
            "memory_total": 42949672960
        }
    ],
    "memory": {
        "total": 251.68415451049805
    }
}
